idessem/__init__.py
idessem/config.py
idessem/py.typed
idessem/dessem/__init__.py
idessem/dessem/areacont.py
idessem/dessem/avl_altqueda.py
idessem/dessem/avl_desvfpha.py
idessem/dessem/avl_estatfpha.py
idessem/dessem/avl_fpha1.py
idessem/dessem/avl_fpha2.py
idessem/dessem/avl_fpha3.py
idessem/dessem/dadvaz.py
idessem/dessem/deflant.py
idessem/dessem/des_log_relato.py
idessem/dessem/desselet.py
idessem/dessem/dessemarq.py
idessem/dessem/dessopc.py
idessem/dessem/entdados.py
idessem/dessem/hidr.py
idessem/dessem/log_inviab.py
idessem/dessem/log_matriz.py
idessem/dessem/operuh.py
idessem/dessem/operut.py
idessem/dessem/pdo_aval_qmaxusih.py
idessem/dessem/pdo_cmobar.py
idessem/dessem/pdo_eco_fcfcortes.py
idessem/dessem/pdo_eco_usih.py
idessem/dessem/pdo_eco_usih_conj.py
idessem/dessem/pdo_eco_usih_polin.py
idessem/dessem/pdo_eolica.py
idessem/dessem/pdo_hidr.py
idessem/dessem/pdo_inter.py
idessem/dessem/pdo_oper_term.py
idessem/dessem/pdo_oper_titulacao_contratos.py
idessem/dessem/pdo_oper_titulacao_usinas.py
idessem/dessem/pdo_oper_tviag_calha.py
idessem/dessem/pdo_oper_uct.py
idessem/dessem/pdo_operacao.py
idessem/dessem/pdo_reserva.py
idessem/dessem/pdo_sist.py
idessem/dessem/pdo_somflux.py
idessem/dessem/pdo_term.py
idessem/dessem/renovaveis.py
idessem/dessem/respot.py
idessem/dessem/termdat.py
idessem/dessem/uch.py
idessem/dessem/modelos/__init__.py
idessem/dessem/modelos/areacont.py
idessem/dessem/modelos/avl_altqueda.py
idessem/dessem/modelos/avl_desvfpha.py
idessem/dessem/modelos/avl_estatfpha.py
idessem/dessem/modelos/avl_fpha1.py
idessem/dessem/modelos/avl_fpha2.py
idessem/dessem/modelos/avl_fpha3.py
idessem/dessem/modelos/dadvaz.py
idessem/dessem/modelos/deflant.py
idessem/dessem/modelos/des_log_relato.py
idessem/dessem/modelos/desselet.py
idessem/dessem/modelos/dessemarq.py
idessem/dessem/modelos/dessopc.py
idessem/dessem/modelos/entdados.py
idessem/dessem/modelos/hidr.py
idessem/dessem/modelos/log_inviab.py
idessem/dessem/modelos/log_matriz.py
idessem-1.0.0.dist-info/METADATA
idessem-1.0.0.dist-info/WHEEL
idessem-1.0.0.dist-info/licenses/LICENSE.md
idessem-1.0.0.dist-info/RECORD
